newpro/__init__.py
newpro-1.0.1.dist-info/DESCRIPTION.rst
newpro-1.0.1.dist-info/METADATA
newpro-1.0.1.dist-info/RECORD
newpro-1.0.1.dist-info/WHEEL
newpro-1.0.1.dist-info/entry_points.txt
newpro-1.0.1.dist-info/metadata.json
newpro-1.0.1.dist-info/top_level.txt
