Metadata-Version: 2.0
Name: newpro
Version: 1.0.1
Summary: A script to create boilerplates for text projects.
Home-page: https://github.com/awesmubarak/newpro
Author: Awes Mubarak
Author-email: awes.mubarak@awesmubarak.com
License: MIT
Keywords: writing markdown pandoc
Platform: UNKNOWN
Classifier: Development Status :: 5 - Production/Stable
Classifier: Intended Audience :: End Users/Desktop
Classifier: License :: OSI Approved :: MIT License
Classifier: Programming Language :: Python
